mltoolbox/__init__.py
mltoolbox/__main__.py
mltoolbox/data_wranglers.py
mltoolbox/estimators.py
mltoolbox/problems.py
mltoolbox/utilities.py
mltoolbox/visualizers.py
mltoolbox-0.0.0.dist-info/LICENSE
mltoolbox-0.0.0.dist-info/METADATA
mltoolbox-0.0.0.dist-info/WHEEL
mltoolbox-0.0.0.dist-info/top_level.txt
mltoolbox-0.0.0.dist-info/RECORD
